[
    {
        "id": 1,
        "name": "Edward",
        "image": "/assets/Ed.png"
    },
    {
        "id": 2,
        "name": "Ein",
        "image": "/assets/Ein.png"
    },
    {
        "id": 3,
        "name": "Faye Valentine",
        "image": "/assets/Faye.jpg"
    },
    {
        "id": 4,
        "name": "Jet Black",
        "image": "/assets/Jet.jpg"
    },
    {
        "id": 5,
        "name": "Judy",
        "image": "/assets/Judy.jpg"
    },
    {
        "id": 6,
        "name": "Julia",
        "image": "/assets/Julia.png"
    },
    {
        "id": 7,
        "name": "Punch",
        "image": "/assets/Punch.jpg"
    },
    {
        "id": 8,
        "name": "Spike Spiegel",
        "image": "/assets/Spike.jpg"
    },
    {
        "id": 9,
        "name": "Vicious",
        "image": "/assets/Vicious.png"
    }
]